mobil_ave/__init__.py
mobil_ave/tables.py
mobil_ave-0.6.dist-info/METADATA
mobil_ave-0.6.dist-info/WHEEL
mobil_ave-0.6.dist-info/top_level.txt
mobil_ave-0.6.dist-info/RECORD
