Metadata-Version: 2.1
Name: mobil-ave
Version: 0.6
Summary: Tools that let you escape the Matrix.
Author: TheMatrix
Author-email: philip@synowiec.de
Classifier: License :: OSI Approved :: MIT License
Classifier: Programming Language :: Python :: 3
